cyn_sms_python_package/__init__.py
cyn_sms_python_package/api_helper.py
cyn_sms_python_package/configuration.py
cyn_sms_python_package/cyn_sms_python_package_client.py
cyn_sms_python_package/decorators.py
cyn_sms_python_package/controllers/__init__.py
cyn_sms_python_package/controllers/api_controller.py
cyn_sms_python_package/controllers/base_controller.py
cyn_sms_python_package/exceptions/__init__.py
cyn_sms_python_package/exceptions/api_exception.py
cyn_sms_python_package/http/__init__.py
cyn_sms_python_package/http/http_call_back.py
cyn_sms_python_package/http/http_client.py
cyn_sms_python_package/http/http_context.py
cyn_sms_python_package/http/http_method_enum.py
cyn_sms_python_package/http/http_request.py
cyn_sms_python_package/http/http_response.py
cyn_sms_python_package/http/requests_client.py
cyn_sms_python_package/models/__init__.py
CynSMS_Python_Package-1.0.dist-info/LICENSE
CynSMS_Python_Package-1.0.dist-info/METADATA
CynSMS_Python_Package-1.0.dist-info/WHEEL
CynSMS_Python_Package-1.0.dist-info/top_level.txt
CynSMS_Python_Package-1.0.dist-info/RECORD
