Metadata-Version: 2.1
Name: CynSMS-Python-Package
Version: 1.0
Summary: This Api is meant for 3rd party integrations
Home-page: https://cynojine.com
Author: kazashim kuzasuwat
Author-email: kazashim@cynojine.com
License: UNKNOWN
Platform: UNKNOWN
Requires-Dist: requests (<3.0,>=2.9.1)
Requires-Dist: jsonpickle (<1.0,>=0.7.1)
Requires-Dist: cachecontrol (<1.0,>=0.11.7)
Requires-Dist: python-dateutil (<3.0,>=2.5.3)
